.coveragerc
.editorconfig
.gitignore
.travis.yml
LICENSE
README.md
pyproject.toml
requirements.txt
requirements_dev.txt
setup.cfg
setup.py
.github/workflows/python-publish.yml
democritus_hashes/__init__.py
democritus_hashes/hashes.py
democritus_hashes/hashes_temp_utils.py
democritus_hashes.egg-info/PKG-INFO
democritus_hashes.egg-info/SOURCES.txt
democritus_hashes.egg-info/dependency_links.txt
democritus_hashes.egg-info/requires.txt
democritus_hashes.egg-info/top_level.txt
democritus_hashes.egg-info/zip-safe
tests/__init__.py
tests/test_hashes.py